{
  "schema_version": "xinao.grok_operational_tools_index.v1",
  "sentinel": "SENTINEL:GROK_OPERATIONAL_TOOLS_INDEX_V1",
  "title_cn": "Grok 岛运维工具索引（合并薄绑）",
  "tools": {
    "session_checkpoint": { "script": "Invoke-GrokSessionContextCheckpoint.ps1", "contract": "grok_session_context_checkpoint.v1.json" },
    "long_workflow": { "script": "Invoke-GrokLongWorkflowBootstrap.ps1", "contract": "grok_long_workflow_runtime.v1.json" },
    "registry_scan": { "script": "Invoke-GrokLocalCapabilityRegistryScan.ps1", "contract": "grok_local_capability_registry.v1.json" },
    "capability_status": { "script": "Get-GrokLocalCapabilityStatus.ps1" },
    "mature_first_governance": {
      "gate_script": "Invoke-GrokMatureFirstGovernanceGate.ps1",
      "loop_contract": "grok_mature_first_governance_loop.v1.json",
      "policy": "grok_mature_first_policy.v1.json",
      "skill": ".grok/skills/mature-first-governance/SKILL.md",
      "human_cn": "C:\\Users\\xx363\\Desktop\\工具胶水宪法\\XINAO_Grok成熟优先治理环_思维宪法_20260709.txt",
      "note_cn": "任何平台/运维/焊路先治理环；OPA精神fail-open"
    },
    "task_entry": { "script": "Invoke-GrokTaskEntry.ps1", "claim_script": "Invoke-GrokTaskEntryClaimDurable.ps1", "status_script": "Get-GrokTaskEntryStatus.ps1", "contract": "grok_task_entry_module.v1.json", "skill": ".grok/skills/task-entry/SKILL.md", "mature_glue": "S/Start-XinaoBaseCompose.ps1 + Status-XinaoBaseCompose + RootIntentLoopDriver" },
    "xinao_base_compose": { "start": "E:\\XINAO_RESEARCH_WORKSPACES\\S\\scripts\\Start-XinaoBaseCompose.ps1", "status": "E:\\XINAO_RESEARCH_WORKSPACES\\S\\scripts\\Status-XinaoBaseCompose.ps1", "stop": "E:\\XINAO_RESEARCH_WORKSPACES\\S\\scripts\\Stop-XinaoBaseCompose.ps1", "compose": "E:\\XINAO_RESEARCH_WORKSPACES\\S\\docker-compose.yml", "claim_sdk": "services.agent_runtime.task_entry_claim", "note_cn": "XINAO_Base V2 unified; spine unchanged" },
    "worker_lane": { "script": "Invoke-GrokCodexSDirectWorkerLane.ps1", "contract": "grok_codex_s_direct_worker_lane_tool.v1.json", "note": "not_333" },
    "desktop_mcp": { "contract": "grok_desktop_operator_windows_mcp.v1.json" },
    "infra_frozen": { "contract": "grok_infrastructure_prerequisite_no_user_menu.v1.json" },
    "no_github_actions": { "contract": "grok_no_github_actions_policy.v1.json" },
    "dual_isomorphism_modular": {
      "contract": "grok_dual_isomorphism_modular_separation.v1.json",
      "weld_script": "Invoke-GrokIsomorphicCapabilityWeld.ps1",
      "skill": ".grok/skills/dual-isomorphism-modular/SKILL.md",
      "evidence": "D:\\XINAO_RESEARCH_RUNTIME\\state\\isomorphic_capability_weld\\latest.json",
      "spec": "D:\\XINAO_RESEARCH_RUNTIME\\specs\\grok_dual_isomorphism_modular_separation_20260709.md",
      "note_cn": "333↔Grok 双方同构；模块化分离；M5 纪律 skills 薄焊"
    },
    "vision_mega_package": {
      "script": "Invoke-GrokVisionMegaPackageLand.ps1",
      "evidence": "D:\\XINAO_RESEARCH_RUNTIME\\state\\vision_mega_package\\latest.json",
      "note_cn": "愿景超级完整大包落盘；抗缩包条目"
    },
    "proactive_evolution_intake": {
      "script": "Invoke-GrokProactiveEvolutionIntake.ps1",
      "evidence": "D:\\XINAO_RESEARCH_RUNTIME\\state\\proactive_evolution_intake\\latest.json",
      "note_cn": "主动进化 intake；gap h7_evolution_honest 读盘"
    },
    "modular_separation_probe": {
      "script": "Invoke-GrokModularSeparationProbe.ps1",
      "evidence": "D:\\XINAO_RESEARCH_RUNTIME\\state\\modular_separation_probe\\latest.json",
      "note_cn": "M1-M4 探活；M5 只 Status"
    },
    "long_workflow_seed_wave11": {
      "script": "Invoke-GrokLongWorkflowRunNext.ps1 -SeedWave11",
      "note_cn": "pending=0 时追加 W11_vision_*；勿复用 W9/W10 id"
    },
    "scan_stack": {
      "script": "Invoke-GrokScanStack.ps1",
      "contract": "grok_scan_stack_capability.v1.json",
      "root": "E:\\XINAO_EXTERNAL_MATURE\\scan-stack",
      "env": "E:\\XINAO_EXTERNAL_MATURE\\scan-stack\\env.ps1",
      "rules": "E:\\XINAO_EXTERNAL_MATURE\\scan-stack\\rules",
      "evidence": "D:\\XINAO_RESEARCH_RUNTIME\\state\\scan_stack\\latest.json",
      "policy_scan_evidence": "D:\\XINAO_RESEARCH_RUNTIME\\state\\weak_strategy_policy_scan\\latest.json",
      "hotpath": "Invoke-GrokScanStack.ps1 -PolicyScan",
      "note_cn": "策略/结构/合同/发现 全局扫（非安全）。规则已挂：-PolicyScan 一键多引擎。-Status/-List/-Smoke/-Run -Tool。排除 Trivy/Grype/OSV/Gitleaks/TruffleHog。",
      "usable_engines_hint": 26,
      "deferred_not_win": ["zoekt", "comby", "openrewrite", "livegrep"]
    },
    "gap_driven_progressor": {
      "script": "Invoke-GrokGapDrivenProgressor.ps1",
      "state_sense": "Get-GrokLocalStateSense.ps1",
      "state_sense_max": "Invoke-GrokStateSenseMax.ps1",
      "loop_guardian": "Invoke-GrokLoopGuardian.ps1",
      "contract": "grok_gap_driven_progressor.v1.json",
      "skill": ".grok/skills/gap-driven-progressor/SKILL.md",
      "auth_shape_cn": "禁止清单制 deny_list_not_allow_list — 非白名单",
      "evidence": "D:\\XINAO_RESEARCH_RUNTIME\\state\\gap_driven_progressor\\latest.json",
      "sense_evidence": "D:\\XINAO_RESEARCH_RUNTIME\\state\\local_state_sense\\latest.json",
      "sense_max_evidence": "D:\\XINAO_RESEARCH_RUNTIME\\state\\state_sense_max\\latest.json",
      "guardian_evidence": "D:\\XINAO_RESEARCH_RUNTIME\\state\\loop_guardian\\latest.json",
      "interject": "D:\\XINAO_RESEARCH_RUNTIME\\readback\\zh\\gap_driven_interject_latest.md",
      "hotpath": "Invoke-GrokStateSenseMax.ps1 ; Invoke-GrokGapDrivenProgressor.ps1 -PushQueue ; Invoke-GrokLoopGuardian.ps1 -ForceProgressor",
      "note_cn": "意图vs现实差距驱动 + 极致状态感知。共享工具池。禁止安全面。非新控制面。"
    },
    "state_sense_max": {
      "script": "Invoke-GrokStateSenseMax.ps1",
      "base": "Get-GrokLocalStateSense.ps1",
      "stack_root": "E:\\XINAO_EXTERNAL_MATURE\\state-sense-stack",
      "env": "E:\\XINAO_EXTERNAL_MATURE\\state-sense-stack\\env.ps1",
      "manifest": "E:\\XINAO_EXTERNAL_MATURE\\state-sense-stack\\MANIFEST.json",
      "evidence": "D:\\XINAO_RESEARCH_RUNTIME\\state\\state_sense_max\\latest.json",
      "shared_cn": "Grok与后台都可用",
      "exclude_security_cn": "无 Trivy/Grype/OSV/Gitleaks/TruffleHog/密钥面/CVE 目标",
      "note_cn": "scc/dive/watchexec/git/docker深/进程端口/AST/依赖工具指针 + scan-stack"
    },
    "exposed_tools_catalog": {
      "script": "Invoke-GrokExposedToolsCatalog.ps1",
      "evidence": "D:\\XINAO_RESEARCH_RUNTIME\\state\\exposed_tools_catalog\\latest.json",
      "readback": "D:\\XINAO_RESEARCH_RUNTIME\\readback\\zh\\exposed_tools_catalog_latest.md",
      "hotpath": "Invoke-GrokExposedToolsCatalog.ps1 -RefreshRegistry",
      "note_cn": "能力面暴露总表：全部工具登记 claim_state + 调用入口；刷新注册表"
    },
    "xinao_mcp_http": {
      "script": "Invoke-GrokStartXinaoMcpHttp.ps1",
      "mature_start": "E:\\XINAO_RESEARCH_WORKSPACES\\S\\scripts\\Start-XinaoMcpHttp.ps1",
      "url": "http://127.0.0.1:19460/mcp",
      "evidence": "D:\\XINAO_RESEARCH_RUNTIME\\state\\xinao_mcp_http\\latest.json",
      "hotpath": "Invoke-GrokStartXinaoMcpHttp.ps1 -Restart",
      "note_cn": "重建/启动 XINAO MCP HTTP；清僵尸 pid；非 333 控制面；GET 可能 406 属 streamable"
    },
    "openhands_smoke": {
      "script": "Invoke-GrokOpenHandsSmokeWhenDocker.ps1",
      "evidence": "D:\\XINAO_RESEARCH_RUNTIME\\state\\openhands_smoke\\latest.json",
      "note_cn": "OpenHands 镜像探活；休眠→可烟测；非默认第二大脑"
    }
  },
  "token_route_note_cn": "省聊天 token：大材料落盘；用户喊搜→原生 WebSearch；见 brain_executor.user_preferences_cn"
}